streamlit_airtable/__init__.py
streamlit_airtable/airtable_connection.py
st_airtable_connection-0.0.4.dist-info/METADATA
st_airtable_connection-0.0.4.dist-info/WHEEL
st_airtable_connection-0.0.4.dist-info/top_level.txt
st_airtable_connection-0.0.4.dist-info/RECORD
