Metadata-Version: 2.1
Name: st-airtable-connection
Version: 0.0.4
Summary: Streamlit Connection for Airtable.
Home-page: https://github.com/marks/streamlit-airtable-connection
Author: Mark Silverberg
Author-email: mark@marksilver.net
License: MIT
Project-URL: Source Code, https://github.com/marks/streamlit-airtable-connection
Classifier: Development Status :: 3 - Alpha
Classifier: Environment :: Console
Classifier: Environment :: Web Environment
Classifier: Intended Audience :: Developers
Classifier: Intended Audience :: Science/Research
Classifier: License :: OSI Approved :: Apache Software License
Classifier: Programming Language :: Python :: 3.10
Requires-Python: >=3.8
Requires-Dist: streamlit >=1.22.0
Requires-Dist: pyairtable >=2.0.0
